setup.py
lagTester/__init__.py
lagTester/lagTester.py
lagTester.egg-info/PKG-INFO
lagTester.egg-info/SOURCES.txt
lagTester.egg-info/dependency_links.txt
lagTester.egg-info/entry_points.txt
lagTester.egg-info/requires.txt
lagTester.egg-info/top_level.txt