Metadata-Version: 1.1
Name: lagTester
Version: 0.0.1
Summary: Script to test gamepad lag time
Home-page: https://github.com/owlz/lagTester
Author: Michael Bann
Author-email: self@bannsecurity.com
License: MIT
Keywords: gamepad controller lag test
Platform: UNKNOWN
Classifier: Development Status :: 5 - Production/Stable
Classifier: Intended Audience :: End Users/Desktop
Classifier: License :: OSI Approved :: MIT License
Classifier: Programming Language :: Python :: 3
Classifier: Programming Language :: Python :: 2
Classifier: Operating System :: POSIX :: Linux
Classifier: Environment :: Console
